odoo8_addon_asterisk_click2dial-8.0.0.4.0.99.dev39-py3.8-nspkg.pth
odoo_addons/asterisk_click2dial/__init__.py
odoo_addons/asterisk_click2dial/__openerp__.py
odoo_addons/asterisk_click2dial/asterisk_click2dial.py
odoo_addons/asterisk_click2dial/asterisk_click2dial_demo.xml
odoo_addons/asterisk_click2dial/asterisk_server_view.xml
odoo_addons/asterisk_click2dial/controller.py
odoo_addons/asterisk_click2dial/requirements.txt
odoo_addons/asterisk_click2dial/res_users_view.xml
odoo_addons/asterisk_click2dial/web_asterisk_click2dial.xml
odoo_addons/asterisk_click2dial/i18n/am.po
odoo_addons/asterisk_click2dial/i18n/ar.po
odoo_addons/asterisk_click2dial/i18n/asterisk_click2dial.pot
odoo_addons/asterisk_click2dial/i18n/bg.po
odoo_addons/asterisk_click2dial/i18n/bs.po
odoo_addons/asterisk_click2dial/i18n/ca.po
odoo_addons/asterisk_click2dial/i18n/ca_ES.po
odoo_addons/asterisk_click2dial/i18n/cs.po
odoo_addons/asterisk_click2dial/i18n/da.po
odoo_addons/asterisk_click2dial/i18n/de.po
odoo_addons/asterisk_click2dial/i18n/el_GR.po
odoo_addons/asterisk_click2dial/i18n/en_GB.po
odoo_addons/asterisk_click2dial/i18n/es.po
odoo_addons/asterisk_click2dial/i18n/es_AR.po
odoo_addons/asterisk_click2dial/i18n/es_CL.po
odoo_addons/asterisk_click2dial/i18n/es_CO.po
odoo_addons/asterisk_click2dial/i18n/es_CR.po
odoo_addons/asterisk_click2dial/i18n/es_DO.po
odoo_addons/asterisk_click2dial/i18n/es_EC.po
odoo_addons/asterisk_click2dial/i18n/es_ES.po
odoo_addons/asterisk_click2dial/i18n/es_MX.po
odoo_addons/asterisk_click2dial/i18n/es_PE.po
odoo_addons/asterisk_click2dial/i18n/es_PY.po
odoo_addons/asterisk_click2dial/i18n/es_VE.po
odoo_addons/asterisk_click2dial/i18n/et.po
odoo_addons/asterisk_click2dial/i18n/eu.po
odoo_addons/asterisk_click2dial/i18n/fa.po
odoo_addons/asterisk_click2dial/i18n/fi.po
odoo_addons/asterisk_click2dial/i18n/fr.po
odoo_addons/asterisk_click2dial/i18n/fr_CA.po
odoo_addons/asterisk_click2dial/i18n/fr_CH.po
odoo_addons/asterisk_click2dial/i18n/gl.po
odoo8_addon_asterisk_click2dial-8.0.0.4.0.99.dev39.dist-info/METADATA
odoo8_addon_asterisk_click2dial-8.0.0.4.0.99.dev39.dist-info/WHEEL
odoo8_addon_asterisk_click2dial-8.0.0.4.0.99.dev39.dist-info/namespace_packages.txt
odoo8_addon_asterisk_click2dial-8.0.0.4.0.99.dev39.dist-info/top_level.txt
odoo8_addon_asterisk_click2dial-8.0.0.4.0.99.dev39.dist-info/RECORD
