Metadata-Version: 2.1
Name: odoo8-addon-asterisk-click2dial
Version: 8.0.0.4.0.99.dev39
Summary: Asterisk-OpenERP connector
Home-page: http://www.akretion.com/
Author: Akretion,Odoo Community Association (OCA)
Author-email: support@odoo-community.org
License: AGPL-3
Platform: UNKNOWN
Classifier: Programming Language :: Python
Classifier: Framework :: Odoo
Classifier: Framework :: Odoo :: 8.0
Classifier: License :: OSI Approved :: GNU Affero General Public License v3
Requires-Python: ~=2.7
Requires-Dist: odoo8-addon-base-phone
Requires-Dist: odoo (<9.0a,>=8.0a)
Requires-Dist: py-Asterisk
